{"edges":[{"source":"business","target":"politics","id":"222","attributes":{"Weight":"0.17900051"},"color":"rgb(214,191,159)","size":0.17900051176548004},{"source":"gadgets","target":"reddit.com","id":"261","attributes":{"Weight":"0.19995432"},"color":"rgb(155,90,106)","size":0.1999543160200119},{"source":"sports","target":"entertainment","id":"238","attributes":{"Weight":"0.10012674"},"color":"rgb(170,202,186)","size":0.10012674331665039},{"source":"worldnews","target":"entertainment","id":"211","attributes":{"Weight":"0.07369498"},"color":"rgb(178,206,187)","size":0.07369498163461685},{"source":"gadgets","target":"science","id":"259","attributes":{"Weight":"0.084632516"},"color":"rgb(175,202,185)","size":0.0846325159072876},{"source":"gaming","target":"entertainment","id":"277","attributes":{"Weight":"0.07775378"},"color":"rgb(190,214,187)","size":0.07775378227233887},{"source":"offbeat","target":"reddit.com","id":"255","attributes":{"Weight":"0.18122697"},"color":"rgb(159,92,106)","size":0.1812269687652588},{"source":"comics","target":"politics","id":"242","attributes":{"Weight":"0.09166667"},"color":"rgb(148,150,156)","size":0.09166666865348816},{"source":"math","target":"programming","id":"217","attributes":{"Weight":"0.18390805"},"color":"rgb(153,190,185)","size":0.18390804529190063},{"source":"AskReddit","target":"reddit.com","id":"202","attributes":{"Weight":"0.19689119"},"color":"rgb(133,76,105)","size":0.196891188621521},{"source":"programming","target":"science","id":"228","attributes":{"Weight":"0.12714085"},"color":"rgb(254,250,188)","size":0.1271408498287201},{"source":"business","target":"technology","id":"223","attributes":{"Weight":"0.098004356"},"color":"rgb(148,188,186)","size":0.09800435602664948},{"source":"videos","target":"politics","id":"256","attributes":{"Weight":"0.10625"},"color":"rgb(145,147,156)","size":0.10625000298023224},{"source":"science","target":"politics","id":"248","attributes":{"Weight":"0.22513252"},"color":"rgb(247,209,158)","size":0.2251325249671936},{"source":"environment","target":"politics","id":"189","attributes":{"Weight":"0.10200669"},"color":"rgb(159,156,156)","size":0.1020066887140274},{"source":"geek","target":"reddit.com","id":"197","attributes":{"Weight":"0.14893617"},"color":"rgb(134,76,105)","size":0.1489361673593521},{"source":"nsfw","target":"reddit.com","id":"185","attributes":{"Weight":"0.22014925"},"color":"rgb(147,85,105)","size":0.22014924883842468},{"source":"WTF","target":"reddit.com","id":"194","attributes":{"Weight":"0.14754099"},"color":"rgb(139,80,105)","size":0.14754098653793335},{"source":"cogsci","target":"politics","id":"199","attributes":{"Weight":"0.097222224"},"color":"rgb(145,147,156)","size":0.0972222238779068},{"source":"worldnews","target":"technology","id":"215","attributes":{"Weight":"0.058341864"},"color":"rgb(117,168,184)","size":0.0583418644964695},{"source":"business","target":"reddit.com","id":"224","attributes":{"Weight":"0.23710139"},"color":"rgb(201,119,108)","size":0.23710139095783234},{"source":"gadgets","target":"politics","id":"260","attributes":{"Weight":"0.08017817"},"color":"rgb(168,162,157)","size":0.0801781713962555},{"source":"obama","target":"reddit.com","id":"196","attributes":{"Weight":"0.16172507"},"color":"rgb(140,80,105)","size":0.16172507405281067},{"source":"AskReddit","target":"politics","id":"201","attributes":{"Weight":"0.10880829"},"color":"rgb(145,148,156)","size":0.10880828648805618},{"source":"linux","target":"reddit.com","id":"236","attributes":{"Weight":"0.23170732"},"color":"rgb(132,75,105)","size":0.23170731961727142},{"source":"entertainment","target":"offbeat","id":"207","attributes":{"Weight":"0.12762882"},"color":"rgb(166,199,186)","size":0.12762881815433502},{"source":"pics","target":"science","id":"232","attributes":{"Weight":"0.073102154"},"color":"rgb(193,213,186)","size":0.07310215383768082},{"source":"science","target":"reddit.com","id":"250","attributes":{"Weight":"0.30749974"},"color":"rgb(234,137,107)","size":0.3074997365474701},{"source":"programming","target":"reddit.com","id":"230","attributes":{"Weight":"0.34973332"},"color":"rgb(234,138,108)","size":0.3497333228588104},{"source":"entertainment","target":"technology","id":"209","attributes":{"Weight":"0.11667442"},"color":"rgb(169,201,186)","size":0.11667442321777344},{"source":"pics","target":"reddit.com","id":"234","attributes":{"Weight":"0.2330079"},"color":"rgb(173,101,106)","size":0.23300789296627045},{"source":"ads","target":"reddit.com","id":"186","attributes":{"Weight":"0.44444445"},"color":"rgb(130,74,105)","size":0.4444444477558136},{"source":"business","target":"science","id":"221","attributes":{"Weight":"0.13681063"},"color":"rgb(221,231,187)","size":0.13681063055992126},{"source":"humor","target":"reddit.com","id":"204","attributes":{"Weight":"0.19101124"},"color":"rgb(131,74,105)","size":0.1910112351179123},{"source":"worldnews","target":"reddit.com","id":"216","attributes":{"Weight":"0.18142101"},"color":"rgb(170,99,106)","size":0.18142101168632507},{"source":"gaming","target":"politics","id":"279","attributes":{"Weight":"0.09287257"},"color":"rgb(195,179,158)","size":0.09287256747484207},{"source":"environment","target":"science","id":"188","attributes":{"Weight":"0.09531773"},"color":"rgb(166,196,185)","size":0.09531772881746292},{"source":"programming","target":"politics","id":"229","attributes":{"Weight":"0.16826166"},"color":"rgb(247,210,159)","size":0.16826166212558746},{"source":"sports","target":"politics","id":"240","attributes":{"Weight":"0.11406844"},"color":"rgb(175,167,157)","size":0.11406844109296799},{"source":"environment","target":"entertainment","id":"187","attributes":{"Weight":"0.07190636"},"color":"rgb(154,191,186)","size":0.07190635800361633},{"source":"sports","target":"science","id":"239","attributes":{"Weight":"0.07731306"},"color":"rgb(182,207,185)","size":0.07731305807828903},{"source":"Economics","target":"science","id":"225","attributes":{"Weight":"0.09443099"},"color":"rgb(166,196,185)","size":0.09443099051713943},{"source":"lolcats","target":"reddit.com","id":"184","attributes":{"Weight":"0.14423077"},"color":"rgb(131,74,105)","size":0.14423076808452606},{"source":"gaming","target":"science","id":"278","attributes":{"Weight":"0.07991361"},"color":"rgb(202,219,186)","size":0.07991360872983932},{"source":"entertainment","target":"reddit.com","id":"210","attributes":{"Weight":"0.27749225"},"color":"rgb(222,132,108)","size":0.2774922549724579},{"source":"videos","target":"reddit.com","id":"257","attributes":{"Weight":"0.1875"},"color":"rgb(132,75,105)","size":0.1875},{"source":"sports","target":"reddit.com","id":"241","attributes":{"Weight":"0.21579415"},"color":"rgb(163,95,106)","size":0.2157941460609436},{"source":"cogsci","target":"science","id":"198","attributes":{"Weight":"0.08796296"},"color":"rgb(152,187,184)","size":0.08796296268701553},{"source":"Music","target":"reddit.com","id":"235","attributes":{"Weight":"0.23076923"},"color":"rgb(131,75,105)","size":0.23076923191547394},{"source":"gaming","target":"reddit.com","id":"280","attributes":{"Weight":"0.25036255"},"color":"rgb(183,107,107)","size":0.2503625452518463},{"source":"entertainment","target":"business","id":"205","attributes":{"Weight":"0.12614295"},"color":"rgb(209,226,188)","size":0.1261429488658905},{"source":"environment","target":"reddit.com","id":"190","attributes":{"Weight":"0.13545151"},"color":"rgb(146,84,105)","size":0.1354515105485916},{"source":"WTF","target":"entertainment","id":"191","attributes":{"Weight":"0.070491806"},"color":"rgb(147,187,185)","size":0.07049180567264557},{"source":"video","target":"reddit.com","id":"203","attributes":{"Weight":"0.17307693"},"color":"rgb(131,75,105)","size":0.17307692766189575},{"source":"funny","target":"reddit.com","id":"275","attributes":{"Weight":"0.14285715"},"color":"rgb(132,75,105)","size":0.1428571492433548},{"source":"Economics","target":"reddit.com","id":"227","attributes":{"Weight":"0.15254237"},"color":"rgb(146,84,105)","size":0.1525423675775528},{"source":"WTF","target":"politics","id":"193","attributes":{"Weight":"0.09836066"},"color":"rgb(152,152,156)","size":0.09836065769195557},{"source":"pics","target":"politics","id":"233","attributes":{"Weight":"0.10590441"},"color":"rgb(186,173,157)","size":0.10590440779924393},{"source":"gadgets","target":"entertainment","id":"258","attributes":{"Weight":"0.09242762"},"color":"rgb(163,197,186)","size":0.09242761880159378},{"source":"bestof","target":"reddit.com","id":"219","attributes":{"Weight":"0.16770187"},"color":"rgb(132,75,105)","size":0.1677018702030182},{"source":"politics","target":"reddit.com","id":"268","attributes":{"Weight":"0.526676"},"color":"rgb(227,97,79)","size":0.5266759991645813},{"source":"offbeat","target":"technology","id":"254","attributes":{"Weight":"0.10891524"},"color":"rgb(105,161,184)","size":0.10891523957252502},{"source":"Economics","target":"politics","id":"226","attributes":{"Weight":"0.13801453"},"color":"rgb(159,156,156)","size":0.1380145251750946},{"source":"atheism","target":"reddit.com","id":"294","attributes":{"Weight":"0.26785713"},"color":"rgb(131,75,105)","size":0.2678571343421936},{"source":"technology","target":"reddit.com","id":"274","attributes":{"Weight":"0.19922465"},"color":"rgb(161,94,106)","size":0.19922465085983276},{"source":"philosophy","target":"reddit.com","id":"293","attributes":{"Weight":"0.1625"},"color":"rgb(131,75,105)","size":0.16249999403953552},{"source":"politics","target":"technology","id":"267","attributes":{"Weight":"0.133866"},"color":"rgb(174,166,157)","size":0.13386599719524384},{"source":"obama","target":"politics","id":"195","attributes":{"Weight":"0.15902965"},"color":"rgb(152,152,156)","size":0.15902964770793915},{"source":"WTF","target":"science","id":"192","attributes":{"Weight":"0.07377049"},"color":"rgb(159,192,184)","size":0.07377049326896667},{"source":"cogsci","target":"reddit.com","id":"200","attributes":{"Weight":"0.125"},"color":"rgb(132,75,105)","size":0.125},{"source":"entertainment","target":"politics","id":"208","attributes":{"Weight":"0.18188936"},"color":"rgb(235,204,159)","size":0.1818893551826477},{"source":"science","target":"offbeat","id":"247","attributes":{"Weight":"0.12376587"},"color":"rgb(178,204,185)","size":0.12376587092876434},{"source":"math","target":"reddit.com","id":"218","attributes":{"Weight":"0.22988506"},"color":"rgb(134,77,105)","size":0.2298850566148758},{"source":"worldnews","target":"politics","id":"214","attributes":{"Weight":"0.16894682"},"color":"rgb(183,171,157)","size":0.16894681751728058},{"source":"offbeat","target":"politics","id":"253","attributes":{"Weight":"0.10821256"},"color":"rgb(171,164,157)","size":0.10821256041526794},{"source":"netsec","target":"reddit.com","id":"276","attributes":{"Weight":"0.13679245"},"color":"rgb(134,77,105)","size":0.13679245114326477},{"source":"worldnews","target":"business","id":"212","attributes":{"Weight":"0.05629478"},"color":"rgb(157,193,186)","size":0.05629478022456169},{"source":"science","target":"technology","id":"249","attributes":{"Weight":"0.12593958"},"color":"rgb(181,206,185)","size":0.12593957781791687},{"source":"comics","target":"reddit.com","id":"243","attributes":{"Weight":"0.16388889"},"color":"rgb(136,78,105)","size":0.16388888657093048},{"source":"pics","target":"entertainment","id":"231","attributes":{"Weight":"0.07685098"},"color":"rgb(181,208,187)","size":0.07685098052024841},{"source":"entertainment","target":"science","id":"206","attributes":{"Weight":"0.14181948"},"color":"rgb(242,244,188)","size":0.14181947708129883},{"source":"xkcd","target":"reddit.com","id":"237","attributes":{"Weight":"0.2647059"},"color":"rgb(130,74,105)","size":0.2647058963775635},{"source":"worldnews","target":"science","id":"213","attributes":{"Weight":"0.08085977"},"color":"rgb(190,211,186)","size":0.08085977286100388}],"nodes":[{"label":"howto","x":-220.57057189941406,"y":-303.9212646484375,"id":"howto","attributes":{"Size":"11.0"},"color":"rgb(45,123,182)","size":25.027992248535156},{"label":"virtualization","x":271.18182373046875,"y":-170.52159118652344,"id":"virtualization","attributes":{"Size":"9.0"},"color":"rgb(44,123,182)","size":25.02239418029785},{"label":"fr","x":-485.7477111816406,"y":203.01419067382812,"id":"fr","attributes":{"Size":"67.0"},"color":"rgb(51,127,182)","size":25.184749603271484},{"label":"gadgets","x":198.7112274169922,"y":80.65691375732422,"id":"gadgets","attributes":{"Size":"461.0"},"color":"rgb(96,155,184)","size":26.287649154663086},{"label":"dailywtf","x":352.3427429199219,"y":-394.26593017578125,"id":"dailywtf","attributes":{"Size":"8.0"},"color":"rgb(44,123,182)","size":25.019594192504883},{"label":"business","x":-284.72320556640625,"y":53.59904479980469,"id":"business","attributes":{"Size":"1274.0"},"color":"rgb(188,213,188)","size":28.563430786132812},{"label":"4chan","x":647.80859375,"y":113.6085433959961,"id":"4chan","attributes":{"Size":"4.0"},"color":"rgb(44,123,182)","size":25.008398056030273},{"label":"polls","x":188.30169677734375,"y":-746.16259765625,"id":"polls","attributes":{"Size":"1.0"},"color":"rgb(44,123,182)","size":25.0},{"label":"it","x":543.4583740234375,"y":-61.8878288269043,"id":"it","attributes":{"Size":"95.0"},"color":"rgb(54,129,182)","size":25.26312828063965},{"label":"astro","x":187.10699462890625,"y":675.3980102539062,"id":"astro","attributes":{"Size":"7.0"},"color":"rgb(44,123,182)","size":25.016796112060547},{"label":"facebook","x":577.102783203125,"y":471.61151123046875,"id":"facebook","attributes":{"Size":"1.0"},"color":"rgb(44,123,182)","size":25.0},{"label":"es","x":-318.20611572265625,"y":607.1095581054688,"id":"es","attributes":{"Size":"16.0"},"color":"rgb(45,124,182)","size":25.041988372802734},{"label":"tech","x":708.60693359375,"y":344.3036193847656,"id":"tech","attributes":{"Size":"21.0"},"color":"rgb(46,124,182)","size":25.055984497070312},{"label":"poll","x":-404.76544189453125,"y":647.3929443359375,"id":"poll","attributes":{"Size":"3.0"},"color":"rgb(44,123,182)","size":25.005598068237305},{"label":"torrents","x":-762.5746459960938,"y":278.39190673828125,"id":"torrents","attributes":{"Size":"11.0"},"color":"rgb(45,123,182)","size":25.027992248535156},{"label":"django","x":-499.1749572753906,"y":-33.3563346862793,"id":"django","attributes":{"Size":"2.0"},"color":"rgb(44,123,182)","size":25.00279998779297},{"label":"yahoo","x":168.20892333984375,"y":-604.205322265625,"id":"yahoo","attributes":{"Size":"18.0"},"color":"rgb(45,124,182)","size":25.04758644104004},{"label":"QuadraIsland","x":-628.3753662109375,"y":-318.6969299316406,"id":"QuadraIsland","attributes":{"Size":"1.0"},"color":"rgb(44,123,182)","size":25.0},{"label":"asia","x":-131.05368041992188,"y":529.956787109375,"id":"asia","attributes":{"Size":"1.0"},"color":"rgb(44,123,182)","size":25.0},{"label":"www","x":742.3199462890625,"y":140.47264099121094,"id":"www","attributes":{"Size":"1.0"},"color":"rgb(44,123,182)","size":25.0},{"label":"norge","x":-670.6107177734375,"y":-60.56769943237305,"id":"norge","attributes":{"Size":"4.0"},"color":"rgb(44,123,182)","size":25.008398056030273},{"label":"photography","x":-317.6087646484375,"y":-659.9800415039062,"id":"photography","attributes":{"Size":"19.0"},"color":"rgb(46,124,182)","size":25.050386428833008},{"label":"blogger","x":-159.51351928710938,"y":-679.4777221679688,"id":"blogger","attributes":{"Size":"1.0"},"color":"rgb(44,123,182)","size":25.0},{"label":"bestof","x":196.9458465576172,"y":180.36300659179688,"id":"bestof","attributes":{"Size":"55.0"},"color":"rgb(50,126,182)","size":25.151159286499023},{"label":"sv","x":418.9989929199219,"y":-709.1862182617188,"id":"sv","attributes":{"Size":"8.0"},"color":"rgb(44,123,182)","size":25.019594192504883},{"label":"conspiracies","x":-158.00315856933594,"y":-594.7018432617188,"id":"conspiracies","attributes":{"Size":"2.0"},"color":"rgb(44,123,182)","size":25.00279998779297},{"label":"worldnews","x":-327.2496643066406,"y":-67.93875122070312,"id":"worldnews","attributes":{"Size":"726.0"},"color":"rgb(126,174,185)","size":27.029447555541992},{"label":"travel","x":-638.2300415039062,"y":407.55206298828125,"id":"travel","attributes":{"Size":"1.0"},"color":"rgb(44,123,182)","size":25.0},{"label":"DIY","x":-438.638427734375,"y":-456.6572570800781,"id":"DIY","attributes":{"Size":"8.0"},"color":"rgb(44,123,182)","size":25.019594192504883},{"label":"bugs","x":-568.8615112304688,"y":-607.54931640625,"id":"bugs","attributes":{"Size":"14.0"},"color":"rgb(45,123,182)","size":25.03639030456543},{"label":"atheism","x":190.94749450683594,"y":-105.60791778564453,"id":"atheism","attributes":{"Size":"44.0"},"color":"rgb(48,126,182)","size":25.1203670501709},{"label":"entertainment","x":-188.00856018066406,"y":71.51815795898438,"id":"entertainment","attributes":{"Size":"1649.0"},"color":"rgb(230,239,189)","size":29.61314582824707},{"label":"youtube","x":727.4535522460938,"y":658.7552490234375,"id":"youtube","attributes":{"Size":"2.0"},"color":"rgb(44,123,182)","size":25.00279998779297},{"label":"Sexy","x":-102.33531951904297,"y":771.644775390625,"id":"Sexy","attributes":{"Size":"1.0"},"color":"rgb(44,123,182)","size":25.0},{"label":"ajax","x":-541.4700927734375,"y":-521.3966674804688,"id":"ajax","attributes":{"Size":"1.0"},"color":"rgb(44,123,182)","size":25.0},{"label":"recipes","x":-648.7508544921875,"y":-515.1165161132812,"id":"recipes","attributes":{"Size":"1.0"},"color":"rgb(44,123,182)","size":25.0},{"label":"microsoft","x":-393.37615966796875,"y":168.76467895507812,"id":"microsoft","attributes":{"Size":"9.0"},"color":"rgb(44,123,182)","size":25.02239418029785},{"label":"australia","x":-727.5786743164062,"y":-319.5296936035156,"id":"australia","attributes":{"Size":"7.0"},"color":"rgb(44,123,182)","size":25.016796112060547},{"label":"science","x":-90.65008544921875,"y":-170.09393310546875,"id":"science","attributes":{"Size":"2445.0"},"color":"rgb(254,249,187)","size":31.841339111328125},{"label":"breakglass","x":467.8531188964844,"y":632.64990234375,"id":"breakglass","attributes":{"Size":"1.0"},"color":"rgb(44,123,182)","size":25.0},{"label":"haskell","x":704.6312866210938,"y":-90.29249572753906,"id":"haskell","attributes":{"Size":"1.0"},"color":"rgb(44,123,182)","size":25.0},{"label":"Conservative","x":552.3554077148438,"y":239.31361389160156,"id":"Conservative","attributes":{"Size":"1.0"},"color":"rgb(44,123,182)","size":25.0},{"label":"kde","x":114.77839660644531,"y":640.1499633789062,"id":"kde","attributes":{"Size":"2.0"},"color":"rgb(44,123,182)","size":25.00279998779297},{"label":"europe","x":410.0088806152344,"y":-519.6383056640625,"id":"europe","attributes":{"Size":"3.0"},"color":"rgb(44,123,182)","size":25.005598068237305},{"label":"hackers","x":-736.7459716796875,"y":110.84673309326172,"id":"hackers","attributes":{"Size":"11.0"},"color":"rgb(45,123,182)","size":25.027992248535156},{"label":"social_bookmarking","x":-738.4174194335938,"y":385.6630859375,"id":"social_bookmarking","attributes":{"Size":"7.0"},"color":"rgb(44,123,182)","size":25.016796112060547},{"label":"comics","x":43.444644927978516,"y":227.3588409423828,"id":"comics","attributes":{"Size":"123.0"},"color":"rgb(57,131,182)","size":25.341506958007812},{"label":"sandbox","x":-647.8993530273438,"y":142.10687255859375,"id":"sandbox","attributes":{"Size":"2.0"},"color":"rgb(44,123,182)","size":25.00279998779297},{"label":"opensource","x":427.9822998046875,"y":764.1244506835938,"id":"opensource","attributes":{"Size":"9.0"},"color":"rgb(44,123,182)","size":25.02239418029785},{"label":"florida","x":492.81964111328125,"y":-123.95613861083984,"id":"florida","attributes":{"Size":"4.0"},"color":"rgb(44,123,182)","size":25.008398056030273},{"label":"productivity","x":-536.19775390625,"y":-342.4363708496094,"id":"productivity","attributes":{"Size":"19.0"},"color":"rgb(46,124,182)","size":25.050386428833008},{"label":"ro","x":-797.9682006835938,"y":176.10400390625,"id":"ro","attributes":{"Size":"4.0"},"color":"rgb(44,123,182)","size":25.008398056030273},{"label":"self","x":214.14117431640625,"y":-427.4908752441406,"id":"self","attributes":{"Size":"5.0"},"color":"rgb(44,123,182)","size":25.01119613647461},{"label":"SocialNews","x":375.4204406738281,"y":615.4823608398438,"id":"SocialNews","attributes":{"Size":"1.0"},"color":"rgb(44,123,182)","size":25.0},{"label":"redsox","x":-134.2070770263672,"y":-766.8534545898438,"id":"redsox","attributes":{"Size":"4.0"},"color":"rgb(44,123,182)","size":25.008398056030273},{"label":"fsm","x":-572.2100219726562,"y":-74.16536712646484,"id":"fsm","attributes":{"Size":"3.0"},"color":"rgb(44,123,182)","size":25.005598068237305},{"label":"Art","x":277.2876281738281,"y":656.0009765625,"id":"Art","attributes":{"Size":"6.0"},"color":"rgb(44,123,182)","size":25.013996124267578},{"label":"canada","x":-654.4312744140625,"y":52.54647445678711,"id":"canada","attributes":{"Size":"7.0"},"color":"rgb(44,123,182)","size":25.016796112060547},{"label":"Cooking","x":-358.8974609375,"y":-154.45716857910156,"id":"Cooking","attributes":{"Size":"6.0"},"color":"rgb(44,123,182)","size":25.013996124267578},{"label":"news","x":24.438570022583008,"y":-768.1055297851562,"id":"news","attributes":{"Size":"44.0"},"color":"rgb(48,126,182)","size":25.1203670501709},{"label":"ko","x":259.47344970703125,"y":-787.5336303710938,"id":"ko","attributes":{"Size":"1.0"},"color":"rgb(44,123,182)","size":25.0},{"label":"Africa","x":-223.57765197753906,"y":657.3948364257812,"id":"Africa","attributes":{"Size":"1.0"},"color":"rgb(44,123,182)","size":25.0},{"label":"books","x":-472.2259216308594,"y":438.20428466796875,"id":"books","attributes":{"Size":"20.0"},"color":"rgb(46,124,182)","size":25.053186416625977},{"label":"perl","x":-534.8365478515625,"y":-434.97991943359375,"id":"perl","attributes":{"Size":"10.0"},"color":"rgb(45,123,182)","size":25.025192260742188},{"label":"conspiracy","x":39.847076416015625,"y":799.669677734375,"id":"conspiracy","attributes":{"Size":"2.0"},"color":"rgb(44,123,182)","size":25.00279998779297},{"label":"Ubuntu","x":444.8861389160156,"y":519.7108764648438,"id":"Ubuntu","attributes":{"Size":"3.0"},"color":"rgb(44,123,182)","size":25.005598068237305},{"label":"sports","x":-43.345977783203125,"y":228.86407470703125,"id":"sports","attributes":{"Size":"594.0"},"color":"rgb(111,165,184)","size":26.659948348999023},{"label":"offbeat","x":-144.03634643554688,"y":-256.56695556640625,"id":"offbeat","attributes":{"Size":"524.0"},"color":"rgb(103,160,184)","size":26.46400260925293},{"label":"iphone","x":-54.361572265625,"y":-595.4794921875,"id":"iphone","attributes":{"Size":"2.0"},"color":"rgb(44,123,182)","size":25.00279998779297},{"label":"Jokes","x":-615.4817504882812,"y":483.9024963378906,"id":"Jokes","attributes":{"Size":"1.0"},"color":"rgb(44,123,182)","size":25.0},{"label":"obama","x":57.52960968017578,"y":161.25003051757812,"id":"obama","attributes":{"Size":"191.0"},"color":"rgb(65,136,182)","size":25.5318546295166},{"label":"McCain","x":-332.13128662109375,"y":438.6663513183594,"id":"McCain","attributes":{"Size":"1.0"},"color":"rgb(44,123,182)","size":25.0},{"label":"japan","x":-492.683349609375,"y":571.2891845703125,"id":"japan","attributes":{"Size":"1.0"},"color":"rgb(44,123,182)","size":25.0},{"label":"food","x":-86.97894287109375,"y":-97.21290588378906,"id":"food","attributes":{"Size":"7.0"},"color":"rgb(44,123,182)","size":25.016796112060547},{"label":"newreddits","x":325.4345397949219,"y":183.725341796875,"id":"newreddits","attributes":{"Size":"2.0"},"color":"rgb(44,123,182)","size":25.00279998779297},{"label":"religion","x":475.4384765625,"y":270.9687194824219,"id":"religion","attributes":{"Size":"5.0"},"color":"rgb(44,123,182)","size":25.01119613647461},{"label":"deutschland","x":-569.75341796875,"y":110.93732452392578,"id":"deutschland","attributes":{"Size":"1.0"},"color":"rgb(44,123,182)","size":25.0},{"label":"tr","x":-457.877685546875,"y":291.98284912109375,"id":"tr","attributes":{"Size":"22.0"},"color":"rgb(46,124,182)","size":25.05878448486328},{"label":"Krugman","x":188.00535583496094,"y":365.5486755371094,"id":"Krugman","attributes":{"Size":"1.0"},"color":"rgb(44,123,182)","size":25.0},{"label":"Christianity","x":-188.77845764160156,"y":414.1356506347656,"id":"Christianity","attributes":{"Size":"8.0"},"color":"rgb(44,123,182)","size":25.019594192504883},{"label":"superhappy","x":167.32749938964844,"y":444.4808044433594,"id":"superhappy","attributes":{"Size":"1.0"},"color":"rgb(44,123,182)","size":25.0},{"label":"Tasers","x":362.85150146484375,"y":538.1388549804688,"id":"Tasers","attributes":{"Size":"1.0"},"color":"rgb(44,123,182)","size":25.0},{"label":"zh","x":441.2205810546875,"y":-277.8538513183594,"id":"zh","attributes":{"Size":"46.0"},"color":"rgb(49,126,182)","size":25.125965118408203},{"label":"environment","x":-176.25885009765625,"y":210.04754638671875,"id":"environment","attributes":{"Size":"304.0"},"color":"rgb(78,144,183)","size":25.848169326782227},{"label":"FourPanelsofFun","x":502.17218017578125,"y":342.9056701660156,"id":"FourPanelsofFun","attributes":{"Size":"1.0"},"color":"rgb(44,123,182)","size":25.0},{"label":"webcomics","x":-257.33721923828125,"y":549.7196655273438,"id":"webcomics","attributes":{"Size":"3.0"},"color":"rgb(44,123,182)","size":25.005598068237305},{"label":"Cplusplus","x":581.9773559570312,"y":595.4039916992188,"id":"Cplusplus","attributes":{"Size":"1.0"},"color":"rgb(44,123,182)","size":25.0},{"label":"cogsci","x":31.323354721069336,"y":-281.08453369140625,"id":"cogsci","attributes":{"Size":"55.0"},"color":"rgb(50,126,182)","size":25.151159286499023},{"label":"happy","x":-213.29421997070312,"y":486.9364929199219,"id":"happy","attributes":{"Size":"264.0"},"color":"rgb(73,141,183)","size":25.7362003326416},{"label":"software","x":-563.6135864257812,"y":206.4814453125,"id":"software","attributes":{"Size":"11.0"},"color":"rgb(45,123,182)","size":25.027992248535156},{"label":"Hillary","x":615.2031860351562,"y":721.4178466796875,"id":"Hillary","attributes":{"Size":"1.0"},"color":"rgb(44,123,182)","size":25.0},{"label":"sex","x":-173.2571563720703,"y":595.7156982421875,"id":"sex","attributes":{"Size":"20.0"},"color":"rgb(46,124,182)","size":25.053186416625977},{"label":"philosophy","x":148.29763793945312,"y":-168.13970947265625,"id":"philosophy","attributes":{"Size":"34.0"},"color":"rgb(47,125,182)","size":25.092374801635742},{"label":"reddit.com","x":43.27482604980469,"y":-10.033087730407715,"id":"reddit.com","attributes":{"Size":"26794.0"},"color":"rgb(215,25,28)","size":100.0},{"label":"video","x":254.0074462890625,"y":-91.18602752685547,"id":"video","attributes":{"Size":"37.0"},"color":"rgb(48,125,182)","size":25.100772857666016},{"label":"scripting","x":-339.8482971191406,"y":514.5765991210938,"id":"scripting","attributes":{"Size":"2.0"},"color":"rgb(44,123,182)","size":25.00279998779297},{"label":"puzzles","x":511.20367431640625,"y":798.2680053710938,"id":"puzzles","attributes":{"Size":"3.0"},"color":"rgb(44,123,182)","size":25.005598068237305},{"label":"Economics","x":67.82244110107422,"y":-206.32711791992188,"id":"Economics","attributes":{"Size":"301.0"},"color":"rgb(78,144,183)","size":25.839771270751953},{"label":"China","x":101.32779693603516,"y":509.78167724609375,"id":"China","attributes":{"Size":"2.0"},"color":"rgb(44,123,182)","size":25.00279998779297},{"label":"podcasts","x":-439.35723876953125,"y":-633.8676147460938,"id":"podcasts","attributes":{"Size":"1.0"},"color":"rgb(44,123,182)","size":25.0},{"label":"anime","x":570.08154296875,"y":-146.8459930419922,"id":"anime","attributes":{"Size":"18.0"},"color":"rgb(45,124,182)","size":25.04758644104004},{"label":"functional","x":109.18342590332031,"y":-735.0746459960938,"id":"functional","attributes":{"Size":"3.0"},"color":"rgb(44,123,182)","size":25.005598068237305},{"label":"web_design","x":-105.66881561279297,"y":678.0640258789062,"id":"web_design","attributes":{"Size":"20.0"},"color":"rgb(46,124,182)","size":25.053186416625977},{"label":"Catalogbiz","x":-646.6256713867188,"y":-413.5356750488281,"id":"Catalogbiz","attributes":{"Size":"2.0"},"color":"rgb(44,123,182)","size":25.00279998779297},{"label":"ja","x":616.5975952148438,"y":384.48638916015625,"id":"ja","attributes":{"Size":"260.0"},"color":"rgb(73,141,183)","size":25.72500228881836},{"label":"leet","x":169.65846252441406,"y":551.4269409179688,"id":"leet","attributes":{"Size":"1.0"},"color":"rgb(44,123,182)","size":25.0},{"label":"code","x":453.91375732421875,"y":-34.942562103271484,"id":"code","attributes":{"Size":"1.0"},"color":"rgb(44,123,182)","size":25.0},{"label":"Libertarian","x":585.4071655273438,"y":-239.37686157226562,"id":"Libertarian","attributes":{"Size":"2.0"},"color":"rgb(44,123,182)","size":25.00279998779297},{"label":"apple","x":310.46478271484375,"y":-686.048583984375,"id":"apple","attributes":{"Size":"9.0"},"color":"rgb(44,123,182)","size":25.02239418029785},{"label":"history","x":185.465087890625,"y":-497.0743713378906,"id":"history","attributes":{"Size":"22.0"},"color":"rgb(46,124,182)","size":25.05878448486328},{"label":"Python","x":547.6025390625,"y":97.63407135009766,"id":"Python","attributes":{"Size":"13.0"},"color":"rgb(45,123,182)","size":25.03359031677246},{"label":"Anarchism","x":468.31451416015625,"y":-574.4551391601562,"id":"Anarchism","attributes":{"Size":"7.0"},"color":"rgb(44,123,182)","size":25.016796112060547},{"label":"inspirational","x":16.31718635559082,"y":658.2627563476562,"id":"inspirational","attributes":{"Size":"10.0"},"color":"rgb(45,123,182)","size":25.025192260742188},{"label":"ru","x":-217.6850128173828,"y":-368.5379638671875,"id":"ru","attributes":{"Size":"77.0"},"color":"rgb(52,128,182)","size":25.21274185180664},{"label":"Music","x":244.32998657226562,"y":25.391735076904297,"id":"Music","attributes":{"Size":"37.0"},"color":"rgb(48,125,182)","size":25.100772857666016},{"label":"javascript","x":665.9440307617188,"y":596.1018676757812,"id":"javascript","attributes":{"Size":"10.0"},"color":"rgb(45,123,182)","size":25.025192260742188},{"label":"l33t","x":-762.2035522460938,"y":-76.27906799316406,"id":"l33t","attributes":{"Size":"421.0"},"color":"rgb(91,152,184)","size":26.17568016052246},{"label":"caregiving","x":522.115478515625,"y":-291.38958740234375,"id":"caregiving","attributes":{"Size":"1.0"},"color":"rgb(44,123,182)","size":25.0},{"label":"TechDispenser","x":726.3027954101562,"y":-185.10968017578125,"id":"TechDispenser","attributes":{"Size":"1.0"},"color":"rgb(44,123,182)","size":25.0},{"label":"scientology","x":90.1120376586914,"y":-660.9904174804688,"id":"scientology","attributes":{"Size":"7.0"},"color":"rgb(44,123,182)","size":25.016796112060547},{"label":"ocaml","x":137.94044494628906,"y":-331.5234375,"id":"ocaml","attributes":{"Size":"7.0"},"color":"rgb(44,123,182)","size":25.016796112060547},{"label":"linux","x":-275.6934509277344,"y":-12.98861312866211,"id":"linux","attributes":{"Size":"47.0"},"color":"rgb(49,126,182)","size":25.128765106201172},{"label":"The_Wire","x":-15.860267639160156,"y":732.1336059570312,"id":"The_Wire","attributes":{"Size":"1.0"},"color":"rgb(44,123,182)","size":25.0},{"label":"bioinformatics","x":-746.2368774414062,"y":-224.7417755126953,"id":"bioinformatics","attributes":{"Size":"2.0"},"color":"rgb(44,123,182)","size":25.00279998779297},{"label":"meta","x":763.7396240234375,"y":443.64111328125,"id":"meta","attributes":{"Size":"3.0"},"color":"rgb(44,123,182)","size":25.005598068237305},{"label":"scala","x":-692.9386596679688,"y":-165.62435913085938,"id":"scala","attributes":{"Size":"1.0"},"color":"rgb(44,123,182)","size":25.0},{"label":"ohwhataworld","x":622.984130859375,"y":194.1183624267578,"id":"ohwhataworld","attributes":{"Size":"2.0"},"color":"rgb(44,123,182)","size":25.00279998779297},{"label":"mjd","x":-56.34902572631836,"y":-711.6566162109375,"id":"mjd","attributes":{"Size":"3.0"},"color":"rgb(44,123,182)","size":25.005598068237305},{"label":"de","x":609.7954711914062,"y":300.65899658203125,"id":"de","attributes":{"Size":"46.0"},"color":"rgb(49,126,182)","size":25.125965118408203},{"label":"ronpaul","x":502.5880432128906,"y":422.88958740234375,"id":"ronpaul","attributes":{"Size":"24.0"},"color":"rgb(46,124,182)","size":25.064382553100586},{"label":"movies","x":38.140846252441406,"y":-482.6341552734375,"id":"movies","attributes":{"Size":"15.0"},"color":"rgb(45,123,182)","size":25.039188385009766},{"label":"Subprime","x":298.2867736816406,"y":501.40673828125,"id":"Subprime","attributes":{"Size":"1.0"},"color":"rgb(44,123,182)","size":25.0},{"label":"onlinegames","x":-673.607421875,"y":316.360107421875,"id":"onlinegames","attributes":{"Size":"3.0"},"color":"rgb(44,123,182)","size":25.005598068237305},{"label":"undead","x":355.2966003417969,"y":-779.1319580078125,"id":"undead","attributes":{"Size":"1.0"},"color":"rgb(44,123,182)","size":25.0},{"label":"nl","x":644.2741088867188,"y":-170.3470916748047,"id":"nl","attributes":{"Size":"11.0"},"color":"rgb(45,123,182)","size":25.027992248535156},{"label":"parislemon","x":247.20167541503906,"y":448.06201171875,"id":"parislemon","attributes":{"Size":"8.0"},"color":"rgb(44,123,182)","size":25.019594192504883},{"label":"osx","x":244.46224975585938,"y":580.1821899414062,"id":"osx","attributes":{"Size":"1.0"},"color":"rgb(44,123,182)","size":25.0},{"label":"whine","x":749.4252319335938,"y":16.733787536621094,"id":"whine","attributes":{"Size":"2.0"},"color":"rgb(44,123,182)","size":25.00279998779297},{"label":"google","x":-740.7344970703125,"y":-443.1222839355469,"id":"google","attributes":{"Size":"12.0"},"color":"rgb(45,123,182)","size":25.030792236328125},{"label":"netsec","x":284.87841796875,"y":-29.107580184936523,"id":"netsec","attributes":{"Size":"92.0"},"color":"rgb(54,129,182)","size":25.254730224609375},{"label":"auto","x":-312.7757873535156,"y":365.43060302734375,"id":"auto","attributes":{"Size":"1.0"},"color":"rgb(44,123,182)","size":25.0},{"label":"area51","x":417.52423095703125,"y":-133.56031799316406,"id":"area51","attributes":{"Size":"4.0"},"color":"rgb(44,123,182)","size":25.008398056030273},{"label":"browsers","x":665.5216674804688,"y":28.458253860473633,"id":"browsers","attributes":{"Size":"10.0"},"color":"rgb(45,123,182)","size":25.025192260742188},{"label":"aws","x":-10.361985206604004,"y":540.87548828125,"id":"aws","attributes":{"Size":"2.0"},"color":"rgb(44,123,182)","size":25.00279998779297},{"label":"wikipedia","x":-261.88018798828125,"y":-505.09295654296875,"id":"wikipedia","attributes":{"Size":"13.0"},"color":"rgb(45,123,182)","size":25.03359031677246},{"label":"hilary","x":326.2303466796875,"y":392.240478515625,"id":"hilary","attributes":{"Size":"2.0"},"color":"rgb(44,123,182)","size":25.00279998779297},{"label":"test","x":258.9328308105469,"y":745.5783081054688,"id":"test","attributes":{"Size":"1.0"},"color":"rgb(44,123,182)","size":25.0},{"label":"gaming","x":-98.37162017822266,"y":179.83062744140625,"id":"gaming","attributes":{"Size":"947.0"},"color":"rgb(151,190,186)","size":27.64807891845703},{"label":"geyik","x":788.235107421875,"y":-88.34246063232422,"id":"geyik","attributes":{"Size":"1.0"},"color":"rgb(44,123,182)","size":25.0},{"label":"fiction","x":-699.1202392578125,"y":210.11428833007812,"id":"fiction","attributes":{"Size":"2.0"},"color":"rgb(44,123,182)","size":25.00279998779297},{"label":"mattculbreth","x":662.6314697265625,"y":-272.4063720703125,"id":"mattculbreth","attributes":{"Size":"3.0"},"color":"rgb(44,123,182)","size":25.005598068237305},{"label":"WTF","x":-6.8194355964660645,"y":-211.57347106933594,"id":"WTF","attributes":{"Size":"184.0"},"color":"rgb(64,135,182)","size":25.51226043701172},{"label":"india","x":513.2429809570312,"y":-681.5330200195312,"id":"india","attributes":{"Size":"18.0"},"color":"rgb(45,124,182)","size":25.04758644104004},{"label":"hiphop","x":-591.9763793945312,"y":5.432422637939453,"id":"hiphop","attributes":{"Size":"5.0"},"color":"rgb(44,123,182)","size":25.01119613647461},{"label":"horror","x":395.3016357421875,"y":-626.2955322265625,"id":"horror","attributes":{"Size":"3.0"},"color":"rgb(44,123,182)","size":25.005598068237305},{"label":"Internet","x":-502.86224365234375,"y":356.6189270019531,"id":"Internet","attributes":{"Size":"1.0"},"color":"rgb(44,123,182)","size":25.0},{"label":"firefox","x":588.9765014648438,"y":7.953886985778809,"id":"firefox","attributes":{"Size":"8.0"},"color":"rgb(44,123,182)","size":25.019594192504883},{"label":"blogs","x":330.0440368652344,"y":799.1740112304688,"id":"blogs","attributes":{"Size":"15.0"},"color":"rgb(45,123,182)","size":25.039188385009766},{"label":"Survival","x":-72.72010803222656,"y":478.2408142089844,"id":"Survival","attributes":{"Size":"1.0"},"color":"rgb(44,123,182)","size":25.0},{"label":"longtext","x":520.6326293945312,"y":543.447021484375,"id":"longtext","attributes":{"Size":"7.0"},"color":"rgb(44,123,182)","size":25.016796112060547},{"label":"craigslist","x":-68.90643310546875,"y":601.2254638671875,"id":"craigslist","attributes":{"Size":"3.0"},"color":"rgb(44,123,182)","size":25.005598068237305},{"label":"pics","x":-181.399658203125,"y":-183.5037841796875,"id":"pics","attributes":{"Size":"782.0"},"color":"rgb(132,178,185)","size":27.18620491027832},{"label":"bnm","x":368.6507263183594,"y":-310.6854248046875,"id":"bnm","attributes":{"Size":"12.0"},"color":"rgb(45,123,182)","size":25.030792236328125},{"label":"Transhuman","x":3.3189315795898438,"y":-651.496337890625,"id":"Transhuman","attributes":{"Size":"3.0"},"color":"rgb(44,123,182)","size":25.005598068237305},{"label":"architecture","x":-46.970211029052734,"y":-517.2005004882812,"id":"architecture","attributes":{"Size":"4.0"},"color":"rgb(44,123,182)","size":25.008398056030273},{"label":"nota","x":56.850650787353516,"y":585.5383911132812,"id":"nota","attributes":{"Size":"4.0"},"color":"rgb(44,123,182)","size":25.008398056030273},{"label":"vid","x":497.9900817871094,"y":-206.5418701171875,"id":"vid","attributes":{"Size":"1.0"},"color":"rgb(44,123,182)","size":25.0},{"label":"ads","x":206.68118286132812,"y":-29.614486694335938,"id":"ads","attributes":{"Size":"16.0"},"color":"rgb(45,124,182)","size":25.041988372802734},{"label":"ruby","x":265.8885498046875,"y":-361.944580078125,"id":"ruby","attributes":{"Size":"115.0"},"color":"rgb(56,131,182)","size":25.31911277770996},{"label":"Drugs","x":375.22509765625,"y":697.227294921875,"id":"Drugs","attributes":{"Size":"4.0"},"color":"rgb(44,123,182)","size":25.008398056030273},{"label":"BSD","x":463.71319580078125,"y":-367.41876220703125,"id":"BSD","attributes":{"Size":"3.0"},"color":"rgb(44,123,182)","size":25.005598068237305},{"label":"sl","x":147.04640197753906,"y":-400.3012390136719,"id":"sl","attributes":{"Size":"6.0"},"color":"rgb(44,123,182)","size":25.013996124267578},{"label":"school","x":-747.6838989257812,"y":21.116512298583984,"id":"school","attributes":{"Size":"1.0"},"color":"rgb(44,123,182)","size":25.0},{"label":"911truth","x":-332.7879943847656,"y":-551.7899780273438,"id":"911truth","attributes":{"Size":"2.0"},"color":"rgb(44,123,182)","size":25.00279998779297},{"label":"xkcd","x":-64.64640808105469,"y":112.0062026977539,"id":"xkcd","attributes":{"Size":"17.0"},"color":"rgb(45,124,182)","size":25.044788360595703},{"label":"philadelphia","x":32.89021682739258,"y":467.05438232421875,"id":"philadelphia","attributes":{"Size":"1.0"},"color":"rgb(44,123,182)","size":25.0},{"label":"joel","x":-418.53936767578125,"y":531.5282592773438,"id":"joel","attributes":{"Size":"38.0"},"color":"rgb(48,125,182)","size":25.10357093811035},{"label":"erlang","x":449.27178955078125,"y":196.7422332763672,"id":"erlang","attributes":{"Size":"37.0"},"color":"rgb(48,125,182)","size":25.100772857666016},{"label":"robotics","x":642.5361328125,"y":-566.4833984375,"id":"robotics","attributes":{"Size":"10.0"},"color":"rgb(45,123,182)","size":25.025192260742188},{"label":"euro","x":110.10485076904297,"y":-519.1121215820312,"id":"euro","attributes":{"Size":"12.0"},"color":"rgb(45,123,182)","size":25.030792236328125},{"label":"ideas","x":-637.517333984375,"y":663.3302001953125,"id":"ideas","attributes":{"Size":"4.0"},"color":"rgb(44,123,182)","size":25.008398056030273},{"label":"videos","x":-269.103515625,"y":-128.380859375,"id":"videos","attributes":{"Size":"56.0"},"color":"rgb(50,126,182)","size":25.15395736694336},{"label":"PHP","x":505.8173828125,"y":26.969823837280273,"id":"PHP","attributes":{"Size":"3.0"},"color":"rgb(44,123,182)","size":25.005598068237305},{"label":"scifi","x":-463.7259826660156,"y":718.5222778320312,"id":"scifi","attributes":{"Size":"16.0"},"color":"rgb(45,124,182)","size":25.041988372802734},{"label":"AskReddit","x":-125.02230072021484,"y":120.67841339111328,"id":"AskReddit","attributes":{"Size":"71.0"},"color":"rgb(51,127,182)","size":25.195947647094727},{"label":"Green","x":709.0615234375,"y":-386.222412109375,"id":"Green","attributes":{"Size":"2.0"},"color":"rgb(44,123,182)","size":25.00279998779297},{"label":"space","x":241.5926513671875,"y":-547.8494873046875,"id":"space","attributes":{"Size":"1.0"},"color":"rgb(44,123,182)","size":25.0},{"label":"Badass","x":629.0665283203125,"y":-70.73794555664062,"id":"Badass","attributes":{"Size":"2.0"},"color":"rgb(44,123,182)","size":25.00279998779297},{"label":"brasil","x":-117.18643188476562,"y":18.5109806060791,"id":"brasil","attributes":{"Size":"11.0"},"color":"rgb(45,123,182)","size":25.027992248535156},{"label":"USPE08","x":317.8574523925781,"y":-492.4508361816406,"id":"USPE08","attributes":{"Size":"3.0"},"color":"rgb(44,123,182)","size":25.005598068237305},{"label":"lisp","x":608.3960571289062,"y":-347.5815734863281,"id":"lisp","attributes":{"Size":"3.0"},"color":"rgb(44,123,182)","size":25.005598068237305},{"label":"ASC","x":700.2353515625,"y":245.04396057128906,"id":"ASC","attributes":{"Size":"4.0"},"color":"rgb(44,123,182)","size":25.008398056030273},{"label":"worldpolitics","x":71.81730651855469,"y":-586.5397338867188,"id":"worldpolitics","attributes":{"Size":"11.0"},"color":"rgb(45,123,182)","size":25.027992248535156},{"label":"qgyh2","x":-320.2483215332031,"y":705.1470336914062,"id":"qgyh2","attributes":{"Size":"1.0"},"color":"rgb(44,123,182)","size":25.0},{"label":"hot","x":415.7467956542969,"y":-440.83624267578125,"id":"hot","attributes":{"Size":"1.0"},"color":"rgb(44,123,182)","size":25.0},{"label":"technology","x":-260.2179870605469,"y":-201.34410095214844,"id":"technology","attributes":{"Size":"569.0"},"color":"rgb(108,163,184)","size":26.589967727661133},{"label":"Pets","x":-165.29156494140625,"y":-488.6729431152344,"id":"Pets","attributes":{"Size":"25.0"},"color":"rgb(46,124,182)","size":25.067182540893555},{"label":"writing","x":-514.5304565429688,"y":-139.7463836669922,"id":"writing","attributes":{"Size":"7.0"},"color":"rgb(44,123,182)","size":25.016796112060547},{"label":"hardware","x":-22.403318405151367,"y":410.06256103515625,"id":"hardware","attributes":{"Size":"10.0"},"color":"rgb(45,123,182)","size":25.025192260742188},{"label":"russia","x":763.8345336914062,"y":-265.1449279785156,"id":"russia","attributes":{"Size":"10.0"},"color":"rgb(45,123,182)","size":25.025192260742188},{"label":"transformers","x":-582.0535888671875,"y":347.8202209472656,"id":"transformers","attributes":{"Size":"2.0"},"color":"rgb(44,123,182)","size":25.00279998779297},{"label":"humor","x":-178.59866333007812,"y":146.9813690185547,"id":"humor","attributes":{"Size":"28.0"},"color":"rgb(47,124,182)","size":25.075578689575195},{"label":"programming","x":-14.03541374206543,"y":157.05262756347656,"id":"programming","attributes":{"Size":"2138.0"},"color":"rgb(254,252,189)","size":30.981971740722656},{"label":"agi","x":528.1173095703125,"y":694.333251953125,"id":"agi","attributes":{"Size":"1.0"},"color":"rgb(44,123,182)","size":25.0},{"label":"government","x":-555.0447387695312,"y":-214.7484588623047,"id":"government","attributes":{"Size":"1.0"},"color":"rgb(44,123,182)","size":25.0},{"label":"vinyl","x":-102.84590148925781,"y":69.79473114013672,"id":"vinyl","attributes":{"Size":"1.0"},"color":"rgb(44,123,182)","size":25.0},{"label":"haiku","x":797.1242065429688,"y":309.84271240234375,"id":"haiku","attributes":{"Size":"5.0"},"color":"rgb(44,123,182)","size":25.01119613647461},{"label":"funny","x":-241.57740783691406,"y":159.5033416748047,"id":"funny","attributes":{"Size":"53.0"},"color":"rgb(49,126,182)","size":25.14556121826172},{"label":"Health","x":-543.8983764648438,"y":645.0996704101562,"id":"Health","attributes":{"Size":"1.0"},"color":"rgb(44,123,182)","size":25.0},{"label":"women","x":506.60699462890625,"y":-481.7261962890625,"id":"women","attributes":{"Size":"14.0"},"color":"rgb(45,123,182)","size":25.03639030456543},{"label":"mobile","x":-618.2352294921875,"y":258.1116638183594,"id":"mobile","attributes":{"Size":"1.0"},"color":"rgb(44,123,182)","size":25.0},{"label":"politics","x":-181.40969848632812,"y":-56.65776443481445,"id":"politics","attributes":{"Size":"11098.0"},"color":"rgb(240,169,130)","size":56.063148498535156},{"label":"aww","x":-617.1358642578125,"y":-147.23126220703125,"id":"aww","attributes":{"Size":"6.0"},"color":"rgb(44,123,182)","size":25.013996124267578},{"label":"lolcats","x":204.54603576660156,"y":-198.78907775878906,"id":"lolcats","attributes":{"Size":"28.0"},"color":"rgb(47,124,182)","size":25.075578689575195},{"label":"hu","x":549.366455078125,"y":-588.3994750976562,"id":"hu","attributes":{"Size":"3.0"},"color":"rgb(44,123,182)","size":25.005598068237305},{"label":"worstof","x":397.7571716308594,"y":441.3374938964844,"id":"worstof","attributes":{"Size":"1.0"},"color":"rgb(44,123,182)","size":25.0},{"label":"england","x":122.2125244140625,"y":746.20166015625,"id":"england","attributes":{"Size":"1.0"},"color":"rgb(44,123,182)","size":25.0},{"label":"math","x":116.11946868896484,"y":190.0332489013672,"id":"math","attributes":{"Size":"88.0"},"color":"rgb(53,129,182)","size":25.243534088134766},{"label":"geek","x":-38.999759674072266,"y":-276.3228759765625,"id":"geek","attributes":{"Size":"81.0"},"color":"rgb(53,128,182)","size":25.223939895629883},{"label":"Edwards","x":541.5778198242188,"y":-400.49273681640625,"id":"Edwards","attributes":{"Size":"1.0"},"color":"rgb(44,123,182)","size":25.0},{"label":"thetansonly","x":378.4397888183594,"y":235.42755126953125,"id":"thetansonly","attributes":{"Size":"1.0"},"color":"rgb(44,123,182)","size":25.0},{"label":"bash","x":232.72601318359375,"y":-654.2156982421875,"id":"bash","attributes":{"Size":"2.0"},"color":"rgb(44,123,182)","size":25.00279998779297},{"label":"nsfw","x":153.13980102539062,"y":132.69618225097656,"id":"nsfw","attributes":{"Size":"323.0"},"color":"rgb(80,145,183)","size":25.901355743408203},{"label":"usa","x":599.2744140625,"y":-482.0478210449219,"id":"usa","attributes":{"Size":"3.0"},"color":"rgb(44,123,182)","size":25.005598068237305},{"label":"cute","x":-221.23643493652344,"y":742.4041137695312,"id":"cute","attributes":{"Size":"1.0"},"color":"rgb(44,123,182)","size":25.0},{"label":"curiosity","x":670.5281372070312,"y":461.5087585449219,"id":"curiosity","attributes":{"Size":"3.0"},"color":"rgb(44,123,182)","size":25.005598068237305},{"label":"startups","x":323.778076171875,"y":-582.2055053710938,"id":"startups","attributes":{"Size":"5.0"},"color":"rgb(44,123,182)","size":25.01119613647461},{"label":"malaysia","x":-493.8088073730469,"y":89.49271392822266,"id":"malaysia","attributes":{"Size":"1.0"},"color":"rgb(44,123,182)","size":25.0},{"label":"rubybr","x":-630.734619140625,"y":562.004638671875,"id":"rubybr","attributes":{"Size":"14.0"},"color":"rgb(45,123,182)","size":25.03639030456543}]}